{"black_box": {"info": {"model": "RandomForestClassifier", "dataset_size": 150, "train_test_split": "70.00% / 30.00%", "input_features": 4, "output_classes": 3}, "performance Data": {"class_performance_data": {"0(setosa)": {"precision": "1.000", "recall": "1.000", "f1_score": "1.000", "support": "13"}, "1(versicolor)": {"precision": "0.842", "recall": "0.941", "f1_score": "0.889", "support": "17"}, "2(virginica)": {"precision": "0.923", "recall": "0.800", "f1_score": "0.857", "support": "15"}}, "accuracy": {"f1_score": "0.911", "support": "45"}, "macro_avg": {"precision": "0.922", "recall": "0.914", "f1_score": "0.915", "support": "45"}, "weighted_avg": {"precision": "0.915", "recall": "0.911", "f1_score": "0.910", "support": "45"}}}, "white_box": {"tree Info": {"method": "Trustee", "model": "DecisionTreeClassifier", "iterations": 10, "sample_size": "30.00%", "size": 5, "depth": 2, "leaves": "3", "input_features": "2 (50.00%)", "output_classes": "3 (100.00%)"}, "fidelity Data": {"class_performance_data": {"0(setosa)": {"precision": "1.000", "recall": "1.000", "f1_score": "1.000", "support": "13"}, "1(versicolor)": {"precision": "1.000", "recall": "0.842", "f1_score": "0.914", "support": "19"}, "2(virginica)": {"precision": "0.812", "recall": "1.000", "f1_score": "0.897", "support": "13"}}, "accuracy": {"f1_score": "0.933", "support": "45"}, "macro_avg": {"precision": "0.938", "recall": "0.947", "f1_score": "0.937", "support": "45"}, "weighted_avg": {"precision": "0.946", "recall": "0.933", "f1_score": "0.934", "support": "45"}}}, "top_k": {"tree Info": {"method": "Trustee", "model": "DecisionTreeClassifier", "iterations": 10, "sample_size": "30.00%", "size": 5, "depth": 2, "leaves": "3", "input_features": "-", "top_k": 10, "output_classes": "3 (100.00%)"}, "fidelity Data": {"class_performance_data": {"0(setosa)": {"precision": "1.000", "recall": "1.000", "f1_score": "1.000", "support": "13"}, "1(versicolor)": {"precision": "1.000", "recall": "0.842", "f1_score": "0.914", "support": "19"}, "2(virginica)": {"precision": "0.812", "recall": "1.000", "f1_score": "0.897", "support": "13"}}, "accuracy": {"f1_score": "0.933", "support": "45"}, "macro_avg": {"precision": "0.938", "recall": "0.947", "f1_score": "0.937", "support": "45"}, "weighted_avg": {"precision": "0.946", "recall": "0.933", "f1_score": "0.934", "support": "45"}}}}